LICENSE
MANIFEST.in
README.md
VERSION
requirements.txt
setup.cfg
setup.py
rhasspy_asr_pocketsphinx.egg-info/PKG-INFO
rhasspy_asr_pocketsphinx.egg-info/SOURCES.txt
rhasspy_asr_pocketsphinx.egg-info/dependency_links.txt
rhasspy_asr_pocketsphinx.egg-info/entry_points.txt
rhasspy_asr_pocketsphinx.egg-info/requires.txt
rhasspy_asr_pocketsphinx.egg-info/top_level.txt
rhasspyasr_pocketsphinx/__init__.py
rhasspyasr_pocketsphinx/__main__.py
rhasspyasr_pocketsphinx/py.typed
rhasspyasr_pocketsphinx/train.py
rhasspyasr_pocketsphinx/transcribe.py